djangocms_typedjs/__init__.py
djangocms_typedjs/apps.py
djangocms_typedjs/cms_plugins.py
djangocms_typedjs/models.py
djangocms_typedjs/settings.py
djangocms_typedjs/locale/__init__.py
djangocms_typedjs/locale/de/LC_MESSAGES/django.po
djangocms_typedjs/locale/es/LC_MESSAGES/django.po
djangocms_typedjs/locale/fr/LC_MESSAGES/django.po
djangocms_typedjs/locale/hi/LC_MESSAGES/django.po
djangocms_typedjs/locale/it/LC_MESSAGES/django.po
djangocms_typedjs/locale/ml/LC_MESSAGES/django.po
djangocms_typedjs/locale/sk/LC_MESSAGES/django.po
djangocms_typedjs/locale/zh-hans/LC_MESSAGES/django.po
djangocms_typedjs/locale/zh-hant/LC_MESSAGES/django.po
djangocms_typedjs/migrations/0001_initial.py
djangocms_typedjs/migrations/0001_initial.pyc
djangocms_typedjs/migrations/__init__.py
djangocms_typedjs/migrations/__init__.pyc
djangocms_typedjs/static/djangocms_typedjs/images/djangocms-typedjs-icon.png
djangocms_typedjs/templates/djangocms_typedjs/_typedjs.html
djangocms_typedjs/tests/__init__.py
djangocms_typedjs/tests/__init__.pyc
djangocms_typedjs/tests/test_models.py
djangocms_typedjs/tests/test_models.pyc
djangocms_typedjs/tests/test_plugins.py
djangocms_typedjs/tests/test_plugins.pyc
djangocms_typedjs/tests/test_settings.py
djangocms_typedjs/tests/test_settings.pyc
djangocms_typedjs-1.0.0.dist-info/DESCRIPTION.rst
djangocms_typedjs-1.0.0.dist-info/METADATA
djangocms_typedjs-1.0.0.dist-info/RECORD
djangocms_typedjs-1.0.0.dist-info/WHEEL
djangocms_typedjs-1.0.0.dist-info/metadata.json
djangocms_typedjs-1.0.0.dist-info/top_level.txt
